grizli/grismconf.py
grizli/catalog.py
grizli/fitting.py
grizli/prep.py
grizli/ds9.py
grizli/multifit.py
grizli/utils.py
grizli/combine.py
grizli/__init__.py
grizli/model.py
grizli/stack.py
grizli/nbutils.py
grizli/jwst_level1.py
grizli/version.py
grizli/jwst_utils.py
grizli/fake_image.py
grizli/aws/tile_mosaic.py
grizli/aws/db.py
grizli/aws/field_tiles.py
grizli/aws/__init__.py
grizli/aws/fit_redshift_lambda.py
grizli/aws/visit_processor.py
grizli/aws/aws_drizzler.py
grizli/aws/lambda_handler.py
grizli/utils_c/interp.cpython-311-x86_64-linux-gnu.so
grizli/utils_c/disperse.cpython-311-x86_64-linux-gnu.so
grizli/utils_c/__init__.py
grizli/utils_c/disperse.c
grizli/utils_c/interp.pyx
grizli/utils_c/interp.c
grizli/utils_c/disperse.pyx
grizli/galfit/psf.py
grizli/galfit/deconvolve.py
grizli/galfit/gfutils.py
grizli/galfit/__init__.py
grizli/galfit/galfit.py
grizli/pipeline/summary.py
grizli/pipeline/auto_script.py
grizli/pipeline/run_MPI.py
grizli/pipeline/reprocess.py
grizli/pipeline/photoz.py
grizli/pipeline/__init__.py
grizli/pipeline/default_params.py
grizli/tests/test_utils.py
grizli/tests/test_jwst.py
grizli/tests/test_cutils.py
grizli/tests/__init__.py
grizli/tests/test_grismconf.py
grizli/tests/test_autoscript.py
grizli/tests/test_fits.py
grizli/tests/data/fit_args.npy
grizli/tests/data/j033216m2743_00152.beams.fits
grizli/tests/data/niriss_jw01324001001_test.beams.fits
grizli/tests/data/wfc3-parse-test.tar.gz
grizli/tests/data/jwst-headers/strip_data.py
grizli/tests/data/jwst-headers/jw42424001001_01101_00001_nrca5_uncal_dispersed_GRISMR_crossing_F356W_rate.fits.gz
grizli/tests/data/jwst-headers/README.rst
grizli/tests/data/jwst-headers/jw42424001001_01101_00001_nrca1_rate.fits.gz
grizli/tests/data/jwst-headers/jw42424001001_01105_00002_nrca5_rate.fits.gz
grizli/tests/data/jwst-headers/det_image_seq1_MIRIMAGE_F560Wexp1_cal.fits.gz
grizli-1.8.5.dist-info/WHEEL
grizli-1.8.5.dist-info/top_level.txt
grizli-1.8.5.dist-info/LICENSE.txt
grizli-1.8.5.dist-info/RECORD
grizli-1.8.5.dist-info/METADATA
