Metadata-Version: 2.1
Name: grizli
Version: 1.8.5
Summary: Grism redshift and line analysis software
Home-page: https://github.com/gbrammer/grizli
Author: G. Brammer
Author-email: gbrammer@gmail.com
License: MIT
Project-URL: Documentation, https://grizli.readthedocs.io/
Project-URL: Source, https://github.com/gbrammer/grizli
Project-URL: Tracker, https://github.com/gbrammer/grizli/issues
Classifier: Development Status :: 3 - Alpha
Classifier: Intended Audience :: Science/Research
Classifier: Topic :: Scientific/Engineering :: Astronomy
Requires-Python: >=3.7
License-File: LICENSE.txt
Requires-Dist: astro-prospector
Requires-Dist: astropy
Requires-Dist: astroquery
Requires-Dist: eazy
Requires-Dist: extinction
Requires-Dist: mastquery (>=1.7.1)
Requires-Dist: matplotlib
Requires-Dist: numpy
Requires-Dist: peakutils
Requires-Dist: regions
Requires-Dist: scikit-image
Requires-Dist: scikit-learn
Requires-Dist: scipy
Requires-Dist: sep
Requires-Dist: shapely
Requires-Dist: sregion (>=1.2.2)
Requires-Dist: stwcs
Requires-Dist: tqdm
Requires-Dist: tristars
Provides-Extra: aws
Requires-Dist: awscli ; extra == 'aws'
Requires-Dist: boto3 ; extra == 'aws'
Requires-Dist: psycopg2-binary ; extra == 'aws'
Requires-Dist: sqlalchemy (<2.0) ; extra == 'aws'
Provides-Extra: docs
Requires-Dist: sphinx ; extra == 'docs'
Requires-Dist: sphinx-astropy ; extra == 'docs'
Provides-Extra: hst
Requires-Dist: reprocess-wfc3 ; extra == 'hst'
Requires-Dist: astroscrappy ; extra == 'hst'
Requires-Dist: drizzlepac ; extra == 'hst'
Requires-Dist: stsci.tools ; extra == 'hst'
Requires-Dist: wfc3tools ; extra == 'hst'
Provides-Extra: jwst
Requires-Dist: jwst ; extra == 'jwst'
Requires-Dist: pysiaf ; extra == 'jwst'
Requires-Dist: grismconf ; extra == 'jwst'
Requires-Dist: numba ; extra == 'jwst'
Requires-Dist: drizzlepac ; extra == 'jwst'
Provides-Extra: test
Requires-Dist: pytest (>=5.1) ; extra == 'test'
Requires-Dist: flake8 ; extra == 'test'
Requires-Dist: drizzlepac ; extra == 'test'
